nomquamgender/__init__.py
nomquamgender/example_names.json
nomquamgender/name_data.json
nomquamgender/nomquamgender.py
nomquamgender-0.1.4.dist-info/LICENSE
nomquamgender-0.1.4.dist-info/METADATA
nomquamgender-0.1.4.dist-info/WHEEL
nomquamgender-0.1.4.dist-info/top_level.txt
nomquamgender-0.1.4.dist-info/RECORD
