Metadata-Version: 2.1
Name: nomquamgender
Version: 0.1.4
Summary: Data and code to support name-based gender classification in scientific research
Home-page: https://github.com/ianvanbuskirk/nomquamgender
Author: Ian Van Buskirk
Author-email: ian@colorado.edu
Classifier: Programming Language :: Python :: 3
Classifier: License :: OSI Approved :: MIT License
Classifier: Operating System :: OS Independent
Requires-Python: >=3.6
License-File: LICENSE
Requires-Dist: unidecode
Requires-Dist: numpy
Requires-Dist: pandas
